skirk/__init__.py
skirk/base_config.py
skirk/source.py
skirk/parser/base_parser.py
skirk/parser/parser_impl.py
skirk/type/base_type_factory.py
skirk/type/type_factory_impl.py
skirk-0.1.1.dist-info/METADATA
skirk-0.1.1.dist-info/WHEEL
skirk-0.1.1.dist-info/top_level.txt
skirk-0.1.1.dist-info/RECORD
