Metadata-Version: 2.4
Name: skirk
Version: 0.1.1
Summary: A lightweight configuration management library that supports loading configurations from multiple sources with type conversion and validation.
Requires-Python: >=3.10
Requires-Dist: pydantic>=2.11.7
Requires-Dist: pyyaml>=6.0.2
Requires-Dist: types-pyyaml>=6.0.12.20250809
